pyutils_aiogram/__init__.py
pyutils_aiogram/core.py
pyutils_aiogram/progress.py
pyutils_aiogram/system_info.py
pyutils_aiogram/utils.py
dmitr_helper-0.1.0.dist-info/METADATA
dmitr_helper-0.1.0.dist-info/WHEEL
dmitr_helper-0.1.0.dist-info/top_level.txt
dmitr_helper-0.1.0.dist-info/RECORD
