Metadata-Version: 2.1
Name: dmitr-helper
Version: 0.1.0
Summary: A collection of useful Python utilities
Home-page: 
Author: KillstreaakX
Author-email: your.email@example.com
Classifier: Programming Language :: Python :: 3
Classifier: License :: OSI Approved :: MIT License
Classifier: Operating System :: OS Independent
Requires-Python: >=3.6
Requires-Dist: pyfiglet
Requires-Dist: tqdm
Requires-Dist: psutil
